aternossuser.py
copied.py
lexica_arts.py
discordapiwebhooks/discordapiwebhooks.py
discordapiwebhooks/setup.py
phpdiscord/phpdiscord.py
aternossuser-0.0.1.dist-info/METADATA
aternossuser-0.0.1.dist-info/WHEEL
aternossuser-0.0.1.dist-info/top_level.txt
aternossuser-0.0.1.dist-info/RECORD
