Metadata-Version: 2.1
Name: aternossuser
Version: 0.0.1
Summary: Модуль использующий, апи Aternos-а с 3 классами Auth, Server, Files.
Home-page: UNKNOWN
License: UNKNOWN
Platform: UNKNOWN
